asilib/__init__.py
asilib/__main__.py
asilib/conjunction.py
asilib/download.py
asilib/imager.py
asilib/imagers.py
asilib/map.py
asilib/skymap.py
asilib/utils.py
asilib/asi/__init__.py
asilib/asi/fake_asi.py
asilib/asi/lamp_phantom.py
asilib/asi/mango.py
asilib/asi/psa_project.py
asilib/asi/rego.py
asilib/asi/themis.py
asilib/asi/trex.py
asilib/data/asi_locations.csv
asilib/data/ne_10m_land.zip
asilib-0.28.0.dist-info/licenses/LICENSE
examples/__init__.py
examples/animate_conjunction.py
examples/animate_fisheye.py
examples/animate_map.py
examples/animate_trex_mosaic.py
examples/collage.py
examples/fisheye_image_arc.py
examples/global_coverage_map.py
examples/keogram_flr.py
examples/keogram_steve.py
examples/lamp_emccd_psa.py
examples/map_arc.py
examples/map_steve.py
tests/__init__.py
tests/mock_footprint.py
tests/test_conjunction.py
tests/test_downloader.py
tests/test_imager.py
tests/test_imagers.py
tests/test_mango.py
tests/test_map.py
tests/test_psa_project.py
tests/test_rego.py
tests/test_skymap.py
tests/test_themis.py
tests/test_trex.py
tests/test_utils.py
asilib-0.28.0.dist-info/METADATA
asilib-0.28.0.dist-info/WHEEL
asilib-0.28.0.dist-info/top_level.txt
asilib-0.28.0.dist-info/RECORD
