Metadata-Version: 2.4
Name: asilib
Version: 0.28.0
Summary: An open source package providing data access and analysis tools for the world's all-sky imager (ASI) data.
Author-email: Mykhaylo Shumko <msshumko@gmail.com>
License: BSD 3-Clause
Project-URL: Homepage, https://aurora-asi-lib.readthedocs.io/
Project-URL: Documentation, https://aurora-asi-lib.readthedocs.io/
Project-URL: Source, https://github.com/mshumko/asilib
Project-URL: Issues, https://github.com/mshumko/asilib/issues
Project-URL: Changelog, https://github.com/mshumko/asilib/blob/main/CHANGELOG.md
Keywords: aurora,all sky imager,REGO,THEMIS,TREx,MANGO
Classifier: Programming Language :: Python :: 3
Classifier: Programming Language :: Python :: 3.11
Classifier: Programming Language :: Python :: 3.12
Classifier: Programming Language :: Python :: 3.13
Classifier: Programming Language :: Python :: 3.14
License-File: LICENSE
Requires-Dist: wheel
Requires-Dist: beautifulsoup4
Requires-Dist: requests
Requires-Dist: numpy
Requires-Dist: scipy>=1.10.0
Requires-Dist: pandas
Requires-Dist: matplotlib<4.0,>=3.7
Requires-Dist: ffmpeg-python
Requires-Dist: pymap3d
Requires-Dist: aacgmv2
Requires-Dist: pyshp>=2.3
Requires-Dist: opencv-python<5.0,>=4.8.0
Requires-Dist: h5py
Dynamic: license-file
